MANIFEST.in
README.rst
README.txt
setup.py
collective/__init__.py
collective.js.backbone.egg-info/PKG-INFO
collective.js.backbone.egg-info/SOURCES.txt
collective.js.backbone.egg-info/dependency_links.txt
collective.js.backbone.egg-info/entry_points.txt
collective.js.backbone.egg-info/namespace_packages.txt
collective.js.backbone.egg-info/not-zip-safe
collective.js.backbone.egg-info/requires.txt
collective.js.backbone.egg-info/top_level.txt
collective/js/__init__.py
collective/js/backbone/__init__.py
collective/js/backbone/configure.zcml
collective/js/backbone/profiles/default/jsregistry.xml
collective/js/backbone/profiles/default/metadata.xml
collective/js/backbone/resources/backbone.min.js
docs/HISTORY.txt
docs/LICENSE.MIT