Metadata-Version: 1.1
Name: collective.js.backbone
Version: 1.0.0.2
Summary: backbone.js for plone
Home-page: https://github.com/collective/collective.js.backbone
Author: Patrick Gerken
Author-email: gerken@patrick-gerken.de
License: MIT
Keywords: javascript plone backbone
Platform: UNKNOWN
Classifier: Framework :: Plone
Classifier: Programming Language :: Python
Classifier: Intended Audience :: Developers
Classifier: License :: OSI Approved :: MIT License
